README.txt
egg_translations.py
setup.cfg
setup.py
EggTranslations.egg-info/PKG-INFO
EggTranslations.egg-info/SOURCES.txt
EggTranslations.egg-info/dependency_links.txt
EggTranslations.egg-info/top_level.txt
EggTranslations.egg-info/zip-safe
EggTranslations.egg-info/i18n/resources.ini
EggTranslations.egg-info/i18n/test_dir/locale/en/catalog.mo
EggTranslations.egg-info/i18n/test_dir/locale/en/catalog.po
EggTranslations.egg-info/i18n/test_dir/locale/en/catalog_alt.mo
EggTranslations.egg-info/i18n/test_dir/locale/en/catalog_alt.po
EggTranslations.egg-info/i18n/test_dir/locale/fr/catalog.mo
EggTranslations.egg-info/i18n/test_dir/locale/fr/catalog.po
EggTranslations.egg-info/i18n/test_dir/locale/fr/catalog_alt.mo
EggTranslations.egg-info/i18n/test_dir/locale/fr/catalog_alt.po
EggTranslations.egg-info/i18n/test_dir/locale/fr/txt_resource.txt
EggTranslations.egg-info/i18n/test_dir/locale/fr_CA/catalog.mo
EggTranslations.egg-info/i18n/test_dir/locale/fr_CA/catalog.po
EggTranslations.egg-info/i18n/test_dir/locale/fr_CA/catalog_alt.mo
EggTranslations.egg-info/i18n/test_dir/locale/fr_CA/catalog_alt.po
EggTranslations.egg-info/i18n/test_dir/resources/img_resource.jpg
EggTranslations.egg-info/i18n/test_dir/resources/txt_resource.txt
EggTranslations.egg-info/test_directory/resources.ini
EggTranslations.egg-info/test_directory/ini_files/resources_bad_header.ini
EggTranslations.egg-info/test_directory/ini_files/resources_bad_key.ini
EggTranslations.egg-info/test_directory/ini_files/resources_bad_mo_path.ini
EggTranslations.egg-info/test_directory/ini_files/resources_bogus_locale.ini
EggTranslations.egg-info/test_directory/ini_files/resources_empty_header.ini
EggTranslations.egg-info/test_directory/ini_files/resources_invalid_header.ini
EggTranslations.egg-info/test_directory/ini_files/resources_multi.ini
EggTranslations.egg-info/test_directory/ini_files/resources_no_mofiles.ini
EggTranslations.egg-info/test_directory/ini_files/resources_no_resources.ini
EggTranslations.egg-info/test_directory/ini_files/resources_shift_jis.ini
EggTranslations.egg-info/test_directory/locale/en/catalog.mo
EggTranslations.egg-info/test_directory/locale/en/catalog.po
EggTranslations.egg-info/test_directory/locale/en/catalog_alt.mo
EggTranslations.egg-info/test_directory/locale/en/catalog_alt.po
EggTranslations.egg-info/test_directory/locale/es_UY/catalog.mo
EggTranslations.egg-info/test_directory/locale/es_UY/catalog.po
EggTranslations.egg-info/test_directory/locale/es_UY/catalog_alt.mo
EggTranslations.egg-info/test_directory/locale/es_UY/catalog_alt.po
EggTranslations.egg-info/test_directory/locale/fr/catalog.mo
EggTranslations.egg-info/test_directory/locale/fr/catalog.po
EggTranslations.egg-info/test_directory/locale/fr/catalog_alt.mo
EggTranslations.egg-info/test_directory/locale/fr/catalog_alt.po
EggTranslations.egg-info/test_directory/locale/fr/txt_resource.txt
EggTranslations.egg-info/test_directory/locale/fr_CA/catalog.mo
EggTranslations.egg-info/test_directory/locale/fr_CA/catalog.po
EggTranslations.egg-info/test_directory/locale/fr_CA/catalog_alt.mo
EggTranslations.egg-info/test_directory/locale/fr_CA/catalog_alt.po
EggTranslations.egg-info/test_directory/locale/ja_JP/catalog.mo
EggTranslations.egg-info/test_directory/locale/ja_JP/catalog.po
EggTranslations.egg-info/test_directory/locale/ja_JP/txt_resource_shift_jis.txt
EggTranslations.egg-info/test_directory/resources/img_resource.jpg
EggTranslations.egg-info/test_directory/resources/txt_resource.txt
tests/_TestCases.py
tests/__init__.py
