Metadata-Version: 1.0
Name: EggTranslations
Version: 1.2.1
Summary: Provides an API for accessing localizations and resources packaged in python eggs
Home-page: http://chandlerproject.org/Projects/EggTranslations
Author: Grant Baillie
Author-email: grant@osafoundation.org
License: Apache License, Version 2.0
Platform: UNKNOWN
Classifier: Development Status :: 4 - Beta
Classifier: Environment :: Console
Classifier: Framework :: Chandler
Classifier: Intended Audience :: Developers
Classifier: License :: OSI Approved :: Apache Software License
Classifier: Operating System :: OS Independent
Classifier: Programming Language :: Python
Classifier: Topic :: Software Development :: Libraries :: Python Modules
Classifier: Topic :: Software Development :: Internationalization
